youtrack_rest_client/__init__.py
youtrack_rest_client/api/__init__.py
youtrack_rest_client/api/default/__init__.py
youtrack_rest_client/api/default/delete_admin_custom_field_settings_bundles_build_id.py
youtrack_rest_client/api/default/delete_admin_custom_field_settings_bundles_enum_id.py
youtrack_rest_client/api/default/delete_admin_custom_field_settings_bundles_owned_field_id.py
youtrack_rest_client/api/default/delete_admin_custom_field_settings_bundles_state_id.py
youtrack_rest_client/api/default/delete_admin_custom_field_settings_bundles_user_id.py
youtrack_rest_client/api/default/delete_admin_custom_field_settings_bundles_user_id_groups_user_group_id.py
youtrack_rest_client/api/default/delete_admin_custom_field_settings_bundles_user_id_individuals_user_id.py
youtrack_rest_client/api/default/delete_admin_custom_field_settings_bundles_version_id.py
youtrack_rest_client/api/default/delete_admin_custom_field_settings_bundles_version_id_values_version_bundle_element_id.py
youtrack_rest_client/api/default/delete_admin_custom_field_settings_custom_fields_id.py
youtrack_rest_client/api/default/delete_admin_projects_id.py
youtrack_rest_client/api/default/delete_admin_projects_id_custom_fields_project_custom_field_id.py
youtrack_rest_client/api/default/delete_admin_projects_id_issues_issue_id.py
youtrack_rest_client/api/default/delete_admin_projects_id_time_tracking_settings_work_item_types_work_item_type_id.py
youtrack_rest_client/api/default/delete_admin_time_tracking_settings_work_item_types_work_item_type_id.py
youtrack_rest_client/api/default/delete_agiles_id.py
youtrack_rest_client/api/default/delete_agiles_id_sprints_sprint_id.py
youtrack_rest_client/api/default/delete_issue_link_types_id.py
youtrack_rest_client/api/default/delete_issue_tags_id.py
youtrack_rest_client/api/default/delete_issues_id.py
youtrack_rest_client/api/default/delete_issues_id_attachments_issue_attachment_id.py
youtrack_rest_client/api/default/delete_issues_id_comments_issue_comment_id.py
youtrack_rest_client-0.1.5.dist-info/WHEEL
youtrack_rest_client-0.1.5.dist-info/METADATA
youtrack_rest_client-0.1.5.dist-info/RECORD
