Metadata-Version: 2.1
Name: youtrack-rest-client
Version: 0.1.5
Summary: A client library for accessing YouTrack REST API
Author: Matvey Ovtsin
Author-email: matvey.ovtsin@jetbrains.com
Requires-Python: >=3.6,<4.0
Classifier: Programming Language :: Python :: 3
Classifier: Programming Language :: Python :: 3.6
Classifier: Programming Language :: Python :: 3.7
Classifier: Programming Language :: Python :: 3.8
Classifier: Programming Language :: Python :: 3.9
Requires-Dist: attrs (>=20.1.0,<22.0.0)
Requires-Dist: httpx (>=0.15.4,<0.19.0)
Requires-Dist: hub-rest-client (>=0.1.5)
Requires-Dist: python-dateutil (>=2.8.0,<3.0.0)
